Metadata-Version: 1.1
Name: exso-kamabay-beautify
Version: 0.1.0
Summary: beautify the appearance of the application on the terminal.
Home-page: https://github.com/ExsoKamabay/terminal-banner
Author: Exso Kamabay
Author-email: UNKNOWN
License: Apache License 2.0
Keywords: beautify,terminal color,color,font,style,terminal
Platform: UNKNOWN
Classifier: License :: OSI Approved :: Apache Software License
Classifier: Operating System :: OS Independent
Classifier: Programming Language :: Python :: 3
Classifier: Topic :: Text Processing :: Fonts
Classifier: Topic :: Text Processing :: General
Classifier: Topic :: Multimedia
Classifier: Topic :: Utilities
